azdatalake/__init__.py
azdatalake/singleton.py
azdatalake-1.1.0.dist-info/LICENSE
azdatalake-1.1.0.dist-info/METADATA
azdatalake-1.1.0.dist-info/WHEEL
azdatalake-1.1.0.dist-info/top_level.txt
azdatalake-1.1.0.dist-info/RECORD
