Metadata-Version: 2.1
Name: azdatalake
Version: 1.1.0
Summary: A package to implement a singleton for azure data storage gen2
Home-page: https://github.com/amedinag32/azdatalake
Author: Alan Medina
Author-email: amedina.escom@hotmail.com
License: UNKNOWN
Platform: UNKNOWN
Classifier: Programming Language :: Python :: 3
Classifier: License :: OSI Approved :: MIT License
Classifier: Operating System :: OS Independent
Requires-Python: >=3.8
Requires-Dist: azure-core (==1.32.0)
Requires-Dist: azure-storage-queue (==12.12.0)
Requires-Dist: certifi (==2024.12.14)
Requires-Dist: cffi (==1.17.1)
Requires-Dist: charset-normalizer (==3.4.0)
Requires-Dist: cryptography (==44.0.0)
Requires-Dist: greenlet (==3.1.1)
Requires-Dist: idna (==3.10)
Requires-Dist: isodate (==0.7.2)
Requires-Dist: numpy (==1.24.4)
Requires-Dist: pandas (==2.0.3)
Requires-Dist: pandasql (==0.7.3)
Requires-Dist: pycparser (==2.22)
Requires-Dist: python-dateutil (==2.9.0.post0)
Requires-Dist: pytz (==2024.2)
Requires-Dist: requests (==2.32.3)
Requires-Dist: six (==1.17.0)
Requires-Dist: typing-extensions (==4.12.2)
Requires-Dist: tzdata (==2024.2)
Requires-Dist: urllib3 (==2.2.3)
